[
    {
        "@_fa": "true",
        "link": [
            {
                "@_fa": "true",
                "@ref": "self",
                "@href": "https://api.elsevier.com/content/abstract/scopus_id/85039809021"
            },
            {
                "@_fa": "true",
                "@ref": "author-affiliation",
                "@href": "https://api.elsevier.com/content/abstract/scopus_id/85039809021?field=author,affiliation"
            },
            {
                "@_fa": "true",
                "@ref": "scopus",
                "@href": "https://www.scopus.com/inward/record.uri?partnerID=HzOxMe3b&scp=85039809021&origin=inward"
            },
            {
                "@_fa": "true",
                "@ref": "scopus-citedby",
                "@href": "https://www.scopus.com/inward/citedby.uri?partnerID=HzOxMe3b&scp=85039809021&origin=inward"
            }
        ],
        "prism:url": "https://api.elsevier.com/content/abstract/scopus_id/85039809021",
        "dc:identifier": "SCOPUS_ID:85039809021",
        "eid": "2-s2.0-85039809021",
        "dc:title": "Effect of CeO<inf>2</inf> on microstructure and wear resistance of TiC bioinert coatings on Ti6Al4V alloy by laser cladding",
        "dc:creator": "Chen T.",
        "prism:publicationName": "Materials",
        "prism:eIssn": "19961944",
        "prism:volume": "11",
        "prism:issueIdentifier": "1",
        "prism:pageRange": null,
        "prism:coverDate": "2017-12-31",
        "prism:coverDisplayDate": "31 December 2017",
        "prism:doi": "10.3390/ma11010058",
        "citedby-count": "38",
        "affiliation": [
            {
                "@_fa": "true",
                "affilname": "Central South University",
                "affiliation-city": "Changsha",
                "affiliation-country": "China"
            }
        ],
        "prism:aggregationType": "Journal",
        "subtype": "ar",
        "subtypeDescription": "Article",
        "article-number": "58",
        "source-id": "76627",
        "openaccess": "1",
        "openaccessFlag": true,
        "freetoread": {
            "value": [
                {
                    "$": "all"
                },
                {
                    "$": "publisherfullgold"
                },
                {
                    "$": "repository"
                },
                {
                    "$": "repositoryvor"
                },
                {
                    "$": "repositoryam"
                }
            ]
        },
        "freetoreadLabel": {
            "value": [
                {
                    "$": "All Open Access"
                },
                {
                    "$": "Gold"
                },
                {
                    "$": "Green"
                }
            ]
        }
    },
    {
        "@_fa": "true",
        "link": [
            {
                "@_fa": "true",
                "@ref": "self",
                "@href": "https://api.elsevier.com/content/abstract/scopus_id/85039802405"
            },
            {
                "@_fa": "true",
                "@ref": "author-affiliation",
                "@href": "https://api.elsevier.com/content/abstract/scopus_id/85039802405?field=author,affiliation"
            },
            {
                "@_fa": "true",
                "@ref": "scopus",
                "@href": "https://www.scopus.com/inward/record.uri?partnerID=HzOxMe3b&scp=85039802405&origin=inward"
            },
            {
                "@_fa": "true",
                "@ref": "scopus-citedby",
                "@href": "https://www.scopus.com/inward/citedby.uri?partnerID=HzOxMe3b&scp=85039802405&origin=inward"
            }
        ],
        "prism:url": "https://api.elsevier.com/content/abstract/scopus_id/85039802405",
        "dc:identifier": "SCOPUS_ID:85039802405",
        "eid": "2-s2.0-85039802405",
        "dc:title": "Corrosion protection of carbon steel by highly processable conducting polyaniline doped phosphoric acid and dodecyl benzenesulfonic acid",
        "dc:creator": "Rouhollahi A.",
        "prism:publicationName": "Analytical and Bioanalytical Electrochemistry",
        "prism:eIssn": "20084226",
        "prism:volume": "9",
        "prism:issueIdentifier": "8",
        "prism:pageRange": "982-999",
        "prism:coverDate": "2017-12-31",
        "prism:coverDisplayDate": "31 December 2017",
        "citedby-count": "2",
        "affiliation": [
            {
                "@_fa": "true",
                "affilname": "K. N. Toosi University of Technology",
                "affiliation-city": "Tehran",
                "affiliation-country": "Iran"
            }
        ],
        "prism:aggregationType": "Journal",
        "subtype": "ar",
        "subtypeDescription": "Article",
        "source-id": "21100224440",
        "openaccess": "0",
        "openaccessFlag": false
    },
    {
        "@_fa": "true",
        "link": [
            {
                "@_fa": "true",
                "@ref": "self",
                "@href": "https://api.elsevier.com/content/abstract/scopus_id/85039791424"
            },
            {
                "@_fa": "true",
                "@ref": "author-affiliation",
                "@href": "https://api.elsevier.com/content/abstract/scopus_id/85039791424?field=author,affiliation"
            },
            {
                "@_fa": "true",
                "@ref": "scopus",
                "@href": "https://www.scopus.com/inward/record.uri?partnerID=HzOxMe3b&scp=85039791424&origin=inward"
            },
            {
                "@_fa": "true",
                "@ref": "scopus-citedby",
                "@href": "https://www.scopus.com/inward/citedby.uri?partnerID=HzOxMe3b&scp=85039791424&origin=inward"
            }
        ],
        "prism:url": "https://api.elsevier.com/content/abstract/scopus_id/85039791424",
        "dc:identifier": "SCOPUS_ID:85039791424",
        "eid": "2-s2.0-85039791424",
        "dc:title": "A study on corrosion inhibitor for mild steel in ethanol fuel blend",
        "dc:creator": "Vu N.S.H.",
        "prism:publicationName": "Materials",
        "prism:eIssn": "19961944",
        "prism:volume": "11",
        "prism:issueIdentifier": "1",
        "prism:pageRange": null,
        "prism:coverDate": "2017-12-31",
        "prism:coverDisplayDate": "31 December 2017",
        "prism:doi": "10.3390/ma11010059",
        "citedby-count": "25",
        "affiliation": [
            {
                "@_fa": "true",
                "affilname": "University of Science, Viet Nam National University Ho Chi Minh City",
                "affiliation-city": "Ho Chi Minh City",
                "affiliation-country": "Viet Nam"
            }
        ],
        "prism:aggregationType": "Journal",
        "subtype": "ar",
        "subtypeDescription": "Article",
        "article-number": "59",
        "source-id": "76627",
        "openaccess": "1",
        "openaccessFlag": true,
        "freetoread": {
            "value": [
                {
                    "$": "all"
                },
                {
                    "$": "publisherfullgold"
                },
                {
                    "$": "repository"
                },
                {
                    "$": "repositoryvor"
                },
                {
                    "$": "repositoryam"
                }
            ]
        },
        "freetoreadLabel": {
            "value": [
                {
                    "$": "All Open Access"
                },
                {
                    "$": "Gold"
                },
                {
                    "$": "Green"
                }
            ]
        }
    },
    {
        "@_fa": "true",
        "link": [
            {
                "@_fa": "true",
                "@ref": "self",
                "@href": "https://api.elsevier.com/content/abstract/scopus_id/85039786441"
            },
            {
                "@_fa": "true",
                "@ref": "author-affiliation",
                "@href": "https://api.elsevier.com/content/abstract/scopus_id/85039786441?field=author,affiliation"
            },
            {
                "@_fa": "true",
                "@ref": "scopus",
                "@href": "https://www.scopus.com/inward/record.uri?partnerID=HzOxMe3b&scp=85039786441&origin=inward"
            },
            {
                "@_fa": "true",
                "@ref": "scopus-citedby",
                "@href": "https://www.scopus.com/inward/citedby.uri?partnerID=HzOxMe3b&scp=85039786441&origin=inward"
            }
        ],
        "prism:url": "https://api.elsevier.com/content/abstract/scopus_id/85039786441",
        "dc:identifier": "SCOPUS_ID:85039786441",
        "eid": "2-s2.0-85039786441",
        "dc:title": "Graphene/nano-sized imprinted polymer/poly(Methyl methacrylate) nanocomposite as a new gas sensor for the determination of nitrobenzene vapors",
        "dc:creator": "Alizadeh T.",
        "prism:publicationName": "Analytical and Bioanalytical Electrochemistry",
        "prism:eIssn": "20084226",
        "prism:volume": "9",
        "prism:issueIdentifier": "8",
        "prism:pageRange": "1070-1079",
        "prism:coverDate": "2017-12-31",
        "prism:coverDisplayDate": "31 December 2017",
        "citedby-count": "1",
        "affiliation": [
            {
                "@_fa": "true",
                "affilname": "University of Tehran",
                "affiliation-city": "Tehran",
                "affiliation-country": "Iran"
            }
        ],
        "prism:aggregationType": "Journal",
        "subtype": "ar",
        "subtypeDescription": "Article",
        "source-id": "21100224440",
        "openaccess": "0",
        "openaccessFlag": false
    },
    {
        "@_fa": "true",
        "link": [
            {
                "@_fa": "true",
                "@ref": "self",
                "@href": "https://api.elsevier.com/content/abstract/scopus_id/85039783845"
            },
            {
                "@_fa": "true",
                "@ref": "author-affiliation",
                "@href": "https://api.elsevier.com/content/abstract/scopus_id/85039783845?field=author,affiliation"
            },
            {
                "@_fa": "true",
                "@ref": "scopus",
                "@href": "https://www.scopus.com/inward/record.uri?partnerID=HzOxMe3b&scp=85039783845&origin=inward"
            },
            {
                "@_fa": "true",
                "@ref": "scopus-citedby",
                "@href": "https://www.scopus.com/inward/citedby.uri?partnerID=HzOxMe3b&scp=85039783845&origin=inward"
            }
        ],
        "prism:url": "https://api.elsevier.com/content/abstract/scopus_id/85039783845",
        "dc:identifier": "SCOPUS_ID:85039783845",
        "eid": "2-s2.0-85039783845",
        "dc:title": "Simultaneous voltammetric determination of uric acid and tryptophan by modified graphite paste electrode with ferrocyanide ions-doped nano resin lewatit fo<inf>36</inf> as a new redox probe",
        "dc:creator": "Ladiz S.",
        "prism:publicationName": "Analytical and Bioanalytical Electrochemistry",
        "prism:eIssn": "20084226",
        "prism:volume": "9",
        "prism:issueIdentifier": "8",
        "prism:pageRange": "1029-1043",
        "prism:coverDate": "2017-12-31",
        "prism:coverDisplayDate": "31 December 2017",
        "citedby-count": "1",
        "affiliation": [
            {
                "@_fa": "true",
                "affilname": "University of Sistan and Baluchestan",
                "affiliation-city": "Zahedan",
                "affiliation-country": "Iran"
            }
        ],
        "prism:aggregationType": "Journal",
        "subtype": "ar",
        "subtypeDescription": "Article",
        "source-id": "21100224440",
        "openaccess": "0",
        "openaccessFlag": false
    },
    {
        "@_fa": "true",
        "link": [
            {
                "@_fa": "true",
                "@ref": "self",
                "@href": "https://api.elsevier.com/content/abstract/scopus_id/85039781830"
            },
            {
                "@_fa": "true",
                "@ref": "author-affiliation",
                "@href": "https://api.elsevier.com/content/abstract/scopus_id/85039781830?field=author,affiliation"
            },
            {
                "@_fa": "true",
                "@ref": "scopus",
                "@href": "https://www.scopus.com/inward/record.uri?partnerID=HzOxMe3b&scp=85039781830&origin=inward"
            },
            {
                "@_fa": "true",
                "@ref": "scopus-citedby",
                "@href": "https://www.scopus.com/inward/citedby.uri?partnerID=HzOxMe3b&scp=85039781830&origin=inward"
            }
        ],
        "prism:url": "https://api.elsevier.com/content/abstract/scopus_id/85039781830",
        "dc:identifier": "SCOPUS_ID:85039781830",
        "eid": "2-s2.0-85039781830",
        "dc:title": "Eco-friendly stability-indicating potentiometric method for the determination of ropinirole hydrochloride",
        "dc:creator": "Merey H.A.",
        "prism:publicationName": "Analytical and Bioanalytical Electrochemistry",
        "prism:eIssn": "20084226",
        "prism:volume": "9",
        "prism:issueIdentifier": "8",
        "prism:pageRange": "1044-1056",
        "prism:coverDate": "2017-12-31",
        "prism:coverDisplayDate": "31 December 2017",
        "citedby-count": "0",
        "affiliation": [
            {
                "@_fa": "true",
                "affilname": "Faculty of Pharmacy",
                "affiliation-city": "Cairo",
                "affiliation-country": "Egypt"
            }
        ],
        "prism:aggregationType": "Journal",
        "subtype": "ar",
        "subtypeDescription": "Article",
        "source-id": "21100224440",
        "openaccess": "0",
        "openaccessFlag": false
    },
    {
        "@_fa": "true",
        "link": [
            {
                "@_fa": "true",
                "@ref": "self",
                "@href": "https://api.elsevier.com/content/abstract/scopus_id/85039778541"
            },
            {
                "@_fa": "true",
                "@ref": "author-affiliation",
                "@href": "https://api.elsevier.com/content/abstract/scopus_id/85039778541?field=author,affiliation"
            },
            {
                "@_fa": "true",
                "@ref": "scopus",
                "@href": "https://www.scopus.com/inward/record.uri?partnerID=HzOxMe3b&scp=85039778541&origin=inward"
            },
            {
                "@_fa": "true",
                "@ref": "scopus-citedby",
                "@href": "https://www.scopus.com/inward/citedby.uri?partnerID=HzOxMe3b&scp=85039778541&origin=inward"
            }
        ],
        "prism:url": "https://api.elsevier.com/content/abstract/scopus_id/85039778541",
        "dc:identifier": "SCOPUS_ID:85039778541",
        "eid": "2-s2.0-85039778541",
        "dc:title": "Simultaneous determination of cu, pb, cd, and, zn in tap water samples in the presence of alizarin: Differential pulse adsorptive stripping voltammetry",
        "dc:creator": "Pardi H.",
        "prism:publicationName": "Analytical and Bioanalytical Electrochemistry",
        "prism:eIssn": "20084226",
        "prism:volume": "9",
        "prism:issueIdentifier": "8",
        "prism:pageRange": "969-981",
        "prism:coverDate": "2017-12-31",
        "prism:coverDisplayDate": "31 December 2017",
        "citedby-count": "18",
        "affiliation": [
            {
                "@_fa": "true",
                "affilname": "Universitas Andalas",
                "affiliation-city": "Padang",
                "affiliation-country": "Indonesia"
            }
        ],
        "prism:aggregationType": "Journal",
        "subtype": "ar",
        "subtypeDescription": "Article",
        "source-id": "21100224440",
        "openaccess": "0",
        "openaccessFlag": false
    },
    {
        "@_fa": "true",
        "link": [
            {
                "@_fa": "true",
                "@ref": "self",
                "@href": "https://api.elsevier.com/content/abstract/scopus_id/85039774269"
            },
            {
                "@_fa": "true",
                "@ref": "author-affiliation",
                "@href": "https://api.elsevier.com/content/abstract/scopus_id/85039774269?field=author,affiliation"
            },
            {
                "@_fa": "true",
                "@ref": "scopus",
                "@href": "https://www.scopus.com/inward/record.uri?partnerID=HzOxMe3b&scp=85039774269&origin=inward"
            },
            {
                "@_fa": "true",
                "@ref": "scopus-citedby",
                "@href": "https://www.scopus.com/inward/citedby.uri?partnerID=HzOxMe3b&scp=85039774269&origin=inward"
            }
        ],
        "prism:url": "https://api.elsevier.com/content/abstract/scopus_id/85039774269",
        "dc:identifier": "SCOPUS_ID:85039774269",
        "eid": "2-s2.0-85039774269",
        "dc:title": "Determination of norepinephrine at a graphite screen printed electrode modified with ag(I) nanocomplex",
        "dc:creator": "Movahedi E.",
        "prism:publicationName": "Analytical and Bioanalytical Electrochemistry",
        "prism:eIssn": "20084226",
        "prism:volume": "9",
        "prism:issueIdentifier": "8",
        "prism:pageRange": "956-968",
        "prism:coverDate": "2017-12-31",
        "prism:coverDisplayDate": "31 December 2017",
        "citedby-count": "2",
        "affiliation": [
            {
                "@_fa": "true",
                "affilname": "University of Sistan and Baluchestan",
                "affiliation-city": "Zahedan",
                "affiliation-country": "Iran"
            }
        ],
        "prism:aggregationType": "Journal",
        "subtype": "ar",
        "subtypeDescription": "Article",
        "source-id": "21100224440",
        "openaccess": "0",
        "openaccessFlag": false
    },
    {
        "@_fa": "true",
        "link": [
            {
                "@_fa": "true",
                "@ref": "self",
                "@href": "https://api.elsevier.com/content/abstract/scopus_id/85039774072"
            },
            {
                "@_fa": "true",
                "@ref": "author-affiliation",
                "@href": "https://api.elsevier.com/content/abstract/scopus_id/85039774072?field=author,affiliation"
            },
            {
                "@_fa": "true",
                "@ref": "scopus",
                "@href": "https://www.scopus.com/inward/record.uri?partnerID=HzOxMe3b&scp=85039774072&origin=inward"
            },
            {
                "@_fa": "true",
                "@ref": "scopus-citedby",
                "@href": "https://www.scopus.com/inward/citedby.uri?partnerID=HzOxMe3b&scp=85039774072&origin=inward"
            }
        ],
        "prism:url": "https://api.elsevier.com/content/abstract/scopus_id/85039774072",
        "dc:identifier": "SCOPUS_ID:85039774072",
        "eid": "2-s2.0-85039774072",
        "dc:title": "Determination of enalapril in pharmaceuticals using electrochemical sensing with amperometric detection",
        "dc:creator": "Mehmeti E.",
        "prism:publicationName": "Analytical and Bioanalytical Electrochemistry",
        "prism:eIssn": "20084226",
        "prism:volume": "9",
        "prism:issueIdentifier": "8",
        "prism:pageRange": "1000-1007",
        "prism:coverDate": "2017-12-31",
        "prism:coverDisplayDate": "31 December 2017",
        "citedby-count": "2",
        "affiliation": [
            {
                "@_fa": "true",
                "affilname": "Universität Graz",
                "affiliation-city": "Graz",
                "affiliation-country": "Austria"
            }
        ],
        "prism:aggregationType": "Journal",
        "subtype": "ar",
        "subtypeDescription": "Article",
        "source-id": "21100224440",
        "openaccess": "0",
        "openaccessFlag": false
    },
    {
        "@_fa": "true",
        "link": [
            {
                "@_fa": "true",
                "@ref": "self",
                "@href": "https://api.elsevier.com/content/abstract/scopus_id/85039771963"
            },
            {
                "@_fa": "true",
                "@ref": "author-affiliation",
                "@href": "https://api.elsevier.com/content/abstract/scopus_id/85039771963?field=author,affiliation"
            },
            {
                "@_fa": "true",
                "@ref": "scopus",
                "@href": "https://www.scopus.com/inward/record.uri?partnerID=HzOxMe3b&scp=85039771963&origin=inward"
            },
            {
                "@_fa": "true",
                "@ref": "scopus-citedby",
                "@href": "https://www.scopus.com/inward/citedby.uri?partnerID=HzOxMe3b&scp=85039771963&origin=inward"
            }
        ],
        "prism:url": "https://api.elsevier.com/content/abstract/scopus_id/85039771963",
        "dc:identifier": "SCOPUS_ID:85039771963",
        "eid": "2-s2.0-85039771963",
        "dc:title": "The effect of coatings and nerve growth factor on attachment and differentiation of Pheochromocytoma Cells",
        "dc:creator": "Orlowska A.",
        "prism:publicationName": "Materials",
        "prism:eIssn": "19961944",
        "prism:volume": "11",
        "prism:issueIdentifier": "1",
        "prism:pageRange": null,
        "prism:coverDate": "2017-12-31",
        "prism:coverDisplayDate": "31 December 2017",
        "prism:doi": "10.3390/ma11010060",
        "citedby-count": "29",
        "affiliation": [
            {
                "@_fa": "true",
                "affilname": "Universitat Rovira i Virgili",
                "affiliation-city": "Tarragona",
                "affiliation-country": "Spain"
            },
            {
                "@_fa": "true",
                "affilname": "Universitätsklinikum Frankfurt",
                "affiliation-city": "Frankfurt am Main",
                "affiliation-country": "Germany"
            }
        ],
        "prism:aggregationType": "Journal",
        "subtype": "ar",
        "subtypeDescription": "Article",
        "article-number": "60",
        "source-id": "76627",
        "openaccess": "1",
        "openaccessFlag": true,
        "freetoread": {
            "value": [
                {
                    "$": "all"
                },
                {
                    "$": "publisherfullgold"
                },
                {
                    "$": "repository"
                },
                {
                    "$": "repositoryvor"
                },
                {
                    "$": "repositoryam"
                }
            ]
        },
        "freetoreadLabel": {
            "value": [
                {
                    "$": "All Open Access"
                },
                {
                    "$": "Gold"
                },
                {
                    "$": "Green"
                }
            ]
        }
    },
    {
        "@_fa": "true",
        "link": [
            {
                "@_fa": "true",
                "@ref": "self",
                "@href": "https://api.elsevier.com/content/abstract/scopus_id/85039771508"
            },
            {
                "@_fa": "true",
                "@ref": "author-affiliation",
                "@href": "https://api.elsevier.com/content/abstract/scopus_id/85039771508?field=author,affiliation"
            },
            {
                "@_fa": "true",
                "@ref": "scopus",
                "@href": "https://www.scopus.com/inward/record.uri?partnerID=HzOxMe3b&scp=85039771508&origin=inward"
            },
            {
                "@_fa": "true",
                "@ref": "scopus-citedby",
                "@href": "https://www.scopus.com/inward/citedby.uri?partnerID=HzOxMe3b&scp=85039771508&origin=inward"
            }
        ],
        "prism:url": "https://api.elsevier.com/content/abstract/scopus_id/85039771508",
        "dc:identifier": "SCOPUS_ID:85039771508",
        "eid": "2-s2.0-85039771508",
        "dc:title": "Isoproturon electrochemical oxidation as an electroanalytic and electrosynthetic system theoretical investigation",
        "dc:creator": "Tkach V.",
        "prism:publicationName": "Analytical and Bioanalytical Electrochemistry",
        "prism:eIssn": "20084226",
        "prism:volume": "9",
        "prism:issueIdentifier": "8",
        "prism:pageRange": "1021-1028",
        "prism:coverDate": "2017-12-31",
        "prism:coverDisplayDate": "31 December 2017",
        "citedby-count": "1",
        "affiliation": [
            {
                "@_fa": "true",
                "affilname": "Yuriy Fedkovych Chernivtsi National University",
                "affiliation-city": "Chernivtsi",
                "affiliation-country": "Ukraine"
            },
            {
                "@_fa": "true",
                "affilname": "Universidade Federal de Mato Grosso do Sul",
                "affiliation-city": "Campo Grande",
                "affiliation-country": "Brazil"
            }
        ],
        "prism:aggregationType": "Journal",
        "subtype": "ar",
        "subtypeDescription": "Article",
        "source-id": "21100224440",
        "openaccess": "0",
        "openaccessFlag": false
    },
    {
        "@_fa": "true",
        "link": [
            {
                "@_fa": "true",
                "@ref": "self",
                "@href": "https://api.elsevier.com/content/abstract/scopus_id/85039769906"
            },
            {
                "@_fa": "true",
                "@ref": "author-affiliation",
                "@href": "https://api.elsevier.com/content/abstract/scopus_id/85039769906?field=author,affiliation"
            },
            {
                "@_fa": "true",
                "@ref": "scopus",
                "@href": "https://www.scopus.com/inward/record.uri?partnerID=HzOxMe3b&scp=85039769906&origin=inward"
            },
            {
                "@_fa": "true",
                "@ref": "scopus-citedby",
                "@href": "https://www.scopus.com/inward/citedby.uri?partnerID=HzOxMe3b&scp=85039769906&origin=inward"
            }
        ],
        "prism:url": "https://api.elsevier.com/content/abstract/scopus_id/85039769906",
        "dc:identifier": "SCOPUS_ID:85039769906",
        "eid": "2-s2.0-85039769906",
        "dc:title": "Simultaneous electrochemical sensing of methyldopa and hydrochlorothiazide using a novel ZNO/AL<inf>2</inf>O<inf>3</inf> nanocomposite modified screen printed electrode",
        "dc:creator": "Zaimbashi R.",
        "prism:publicationName": "Analytical and Bioanalytical Electrochemistry",
        "prism:eIssn": "20084226",
        "prism:volume": "9",
        "prism:issueIdentifier": "8",
        "prism:pageRange": "1008-1020",
        "prism:coverDate": "2017-12-31",
        "prism:coverDisplayDate": "31 December 2017",
        "citedby-count": "4",
        "affiliation": [
            {
                "@_fa": "true",
                "affilname": "Graduate University of Advanced Technology",
                "affiliation-city": "Kerman",
                "affiliation-country": "Iran"
            }
        ],
        "prism:aggregationType": "Journal",
        "subtype": "ar",
        "subtypeDescription": "Article",
        "source-id": "21100224440",
        "openaccess": "0",
        "openaccessFlag": false
    },
    {
        "@_fa": "true",
        "link": [
            {
                "@_fa": "true",
                "@ref": "self",
                "@href": "https://api.elsevier.com/content/abstract/scopus_id/85039761397"
            },
            {
                "@_fa": "true",
                "@ref": "author-affiliation",
                "@href": "https://api.elsevier.com/content/abstract/scopus_id/85039761397?field=author,affiliation"
            },
            {
                "@_fa": "true",
                "@ref": "scopus",
                "@href": "https://www.scopus.com/inward/record.uri?partnerID=HzOxMe3b&scp=85039761397&origin=inward"
            },
            {
                "@_fa": "true",
                "@ref": "scopus-citedby",
                "@href": "https://www.scopus.com/inward/citedby.uri?partnerID=HzOxMe3b&scp=85039761397&origin=inward"
            }
        ],
        "prism:url": "https://api.elsevier.com/content/abstract/scopus_id/85039761397",
        "dc:identifier": "SCOPUS_ID:85039761397",
        "eid": "2-s2.0-85039761397",
        "dc:title": "Tungsten oxide (WO<inf>3</inf>) modified carbon paste electrode for electrochemical investigation of dopamine in presence of uric acid and folic acid",
        "dc:creator": "Ashoka N.B.",
        "prism:publicationName": "Analytical and Bioanalytical Electrochemistry",
        "prism:eIssn": "20084226",
        "prism:volume": "9",
        "prism:issueIdentifier": "8",
        "prism:pageRange": "1057-1069",
        "prism:coverDate": "2017-12-31",
        "prism:coverDisplayDate": "31 December 2017",
        "citedby-count": "2",
        "affiliation": [
            {
                "@_fa": "true",
                "affilname": "Kuvempu University",
                "affiliation-city": "Shivamogga",
                "affiliation-country": "India"
            }
        ],
        "prism:aggregationType": "Journal",
        "subtype": "ar",
        "subtypeDescription": "Article",
        "source-id": "21100224440",
        "openaccess": "0",
        "openaccessFlag": false
    },
    {
        "@_fa": "true",
        "link": [
            {
                "@_fa": "true",
                "@ref": "self",
                "@href": "https://api.elsevier.com/content/abstract/scopus_id/85039757131"
            },
            {
                "@_fa": "true",
                "@ref": "author-affiliation",
                "@href": "https://api.elsevier.com/content/abstract/scopus_id/85039757131?field=author,affiliation"
            },
            {
                "@_fa": "true",
                "@ref": "scopus",
                "@href": "https://www.scopus.com/inward/record.uri?partnerID=HzOxMe3b&scp=85039757131&origin=inward"
            },
            {
                "@_fa": "true",
                "@ref": "scopus-citedby",
                "@href": "https://www.scopus.com/inward/citedby.uri?partnerID=HzOxMe3b&scp=85039757131&origin=inward"
            }
        ],
        "prism:url": "https://api.elsevier.com/content/abstract/scopus_id/85039757131",
        "dc:identifier": "SCOPUS_ID:85039757131",
        "eid": "2-s2.0-85039757131",
        "dc:title": "An experimental investigation on mechanical behaviour of siCp reinforced Al 6061 MMC using squeeze casting process",
        "dc:creator": "Singh M.",
        "prism:publicationName": "International Journal of Mechanical and Production Engineering Research and Development",
        "prism:issn": "22496890",
        "prism:eIssn": "22498001",
        "prism:volume": "7",
        "prism:issueIdentifier": "6",
        "prism:pageRange": "663-668",
        "prism:coverDate": "2017-12-31",
        "prism:coverDisplayDate": "31 December 2017",
        "prism:doi": "10.24247/ijmperddec201774",
        "citedby-count": "84",
        "affiliation": [
            {
                "@_fa": "true",
                "affilname": "Amity University",
                "affiliation-city": "Noida",
                "affiliation-country": "India"
            }
        ],
        "prism:aggregationType": "Journal",
        "subtype": "ar",
        "subtypeDescription": "Article",
        "source-id": "21100814505",
        "openaccess": "1",
        "openaccessFlag": true,
        "freetoread": {
            "value": [
                {
                    "$": "all"
                },
                {
                    "$": "publisherfullgold"
                }
            ]
        },
        "freetoreadLabel": {
            "value": [
                {
                    "$": "All Open Access"
                },
                {
                    "$": "Gold"
                }
            ]
        }
    },
    {
        "@_fa": "true",
        "link": [
            {
                "@_fa": "true",
                "@ref": "self",
                "@href": "https://api.elsevier.com/content/abstract/scopus_id/85039747932"
            },
            {
                "@_fa": "true",
                "@ref": "author-affiliation",
                "@href": "https://api.elsevier.com/content/abstract/scopus_id/85039747932?field=author,affiliation"
            },
            {
                "@_fa": "true",
                "@ref": "scopus",
                "@href": "https://www.scopus.com/inward/record.uri?partnerID=HzOxMe3b&scp=85039747932&origin=inward"
            },
            {
                "@_fa": "true",
                "@ref": "scopus-citedby",
                "@href": "https://www.scopus.com/inward/citedby.uri?partnerID=HzOxMe3b&scp=85039747932&origin=inward"
            }
        ],
        "prism:url": "https://api.elsevier.com/content/abstract/scopus_id/85039747932",
        "dc:identifier": "SCOPUS_ID:85039747932",
        "eid": "2-s2.0-85039747932",
        "dc:title": "Advanced pulmonary arterial hypertension: Mechanical support and lung transplantation",
        "dc:creator": "Bartolome S.",
        "prism:publicationName": "European Respiratory Review",
        "prism:issn": "09059180",
        "prism:eIssn": "16000617",
        "prism:volume": "26",
        "prism:issueIdentifier": "146",
        "prism:pageRange": null,
        "prism:coverDate": "2017-12-31",
        "prism:coverDisplayDate": "31 December 2017",
        "prism:doi": "10.1183/16000617.0089-2017",
        "citedby-count": "24",
        "affiliation": [
            {
                "@_fa": "true",
                "affilname": "UT Southwestern Medical Center",
                "affiliation-city": "Dallas",
                "affiliation-country": "United States"
            }
        ],
        "pubmed-id": "29263172",
        "prism:aggregationType": "Journal",
        "subtype": "re",
        "subtypeDescription": "Review",
        "article-number": "170089",
        "source-id": "18476",
        "openaccess": "1",
        "openaccessFlag": true,
        "freetoread": {
            "value": [
                {
                    "$": "all"
                },
                {
                    "$": "publisherfullgold"
                }
            ]
        },
        "freetoreadLabel": {
            "value": [
                {
                    "$": "All Open Access"
                },
                {
                    "$": "Gold"
                }
            ]
        }
    },
    {
        "@_fa": "true",
        "link": [
            {
                "@_fa": "true",
                "@ref": "self",
                "@href": "https://api.elsevier.com/content/abstract/scopus_id/85039747157"
            },
            {
                "@_fa": "true",
                "@ref": "author-affiliation",
                "@href": "https://api.elsevier.com/content/abstract/scopus_id/85039747157?field=author,affiliation"
            },
            {
                "@_fa": "true",
                "@ref": "scopus",
                "@href": "https://www.scopus.com/inward/record.uri?partnerID=HzOxMe3b&scp=85039747157&origin=inward"
            },
            {
                "@_fa": "true",
                "@ref": "scopus-citedby",
                "@href": "https://www.scopus.com/inward/citedby.uri?partnerID=HzOxMe3b&scp=85039747157&origin=inward"
            }
        ],
        "prism:url": "https://api.elsevier.com/content/abstract/scopus_id/85039747157",
        "dc:identifier": "SCOPUS_ID:85039747157",
        "eid": "2-s2.0-85039747157",
        "dc:title": "High-order optical nonlinearities in plasmonic nanocomposites—a review",
        "dc:creator": "Reyna A.S.",
        "prism:publicationName": "Advances in Optics and Photonics",
        "prism:eIssn": "19438206",
        "prism:volume": "9",
        "prism:issueIdentifier": "4",
        "prism:pageRange": "720-774",
        "prism:coverDate": "2017-12-31",
        "prism:coverDisplayDate": "31 December 2017",
        "prism:doi": "10.1364/AOP.9.000720",
        "citedby-count": "79",
        "affiliation": [
            {
                "@_fa": "true",
                "affilname": "Universidade Federal de Pernambuco",
                "affiliation-city": "Recife",
                "affiliation-country": "Brazil"
            }
        ],
        "prism:aggregationType": "Journal",
        "subtype": "re",
        "subtypeDescription": "Review",
        "source-id": "21100228100",
        "openaccess": "0",
        "openaccessFlag": false
    },
    {
        "@_fa": "true",
        "link": [
            {
                "@_fa": "true",
                "@ref": "self",
                "@href": "https://api.elsevier.com/content/abstract/scopus_id/85039744720"
            },
            {
                "@_fa": "true",
                "@ref": "author-affiliation",
                "@href": "https://api.elsevier.com/content/abstract/scopus_id/85039744720?field=author,affiliation"
            },
            {
                "@_fa": "true",
                "@ref": "scopus",
                "@href": "https://www.scopus.com/inward/record.uri?partnerID=HzOxMe3b&scp=85039744720&origin=inward"
            },
            {
                "@_fa": "true",
                "@ref": "scopus-citedby",
                "@href": "https://www.scopus.com/inward/citedby.uri?partnerID=HzOxMe3b&scp=85039744720&origin=inward"
            }
        ],
        "prism:url": "https://api.elsevier.com/content/abstract/scopus_id/85039744720",
        "dc:identifier": "SCOPUS_ID:85039744720",
        "eid": "2-s2.0-85039744720",
        "dc:title": "Sensing with periodic nanohole arrays",
        "dc:creator": "Blanchard-Dionne A.P.",
        "prism:publicationName": "Advances in Optics and Photonics",
        "prism:eIssn": "19438206",
        "prism:volume": "9",
        "prism:issueIdentifier": "4",
        "prism:pageRange": "891-940",
        "prism:coverDate": "2017-12-31",
        "prism:coverDisplayDate": "31 December 2017",
        "prism:doi": "10.1364/AOP.9.000891",
        "citedby-count": "48",
        "affiliation": [
            {
                "@_fa": "true",
                "affilname": "Polytechnique Montréal",
                "affiliation-city": "Montreal",
                "affiliation-country": "Canada"
            }
        ],
        "prism:aggregationType": "Journal",
        "subtype": "ar",
        "subtypeDescription": "Article",
        "source-id": "21100228100",
        "openaccess": "0",
        "openaccessFlag": false
    },
    {
        "@_fa": "true",
        "link": [
            {
                "@_fa": "true",
                "@ref": "self",
                "@href": "https://api.elsevier.com/content/abstract/scopus_id/85039733769"
            },
            {
                "@_fa": "true",
                "@ref": "author-affiliation",
                "@href": "https://api.elsevier.com/content/abstract/scopus_id/85039733769?field=author,affiliation"
            },
            {
                "@_fa": "true",
                "@ref": "scopus",
                "@href": "https://www.scopus.com/inward/record.uri?partnerID=HzOxMe3b&scp=85039733769&origin=inward"
            },
            {
                "@_fa": "true",
                "@ref": "scopus-citedby",
                "@href": "https://www.scopus.com/inward/citedby.uri?partnerID=HzOxMe3b&scp=85039733769&origin=inward"
            }
        ],
        "prism:url": "https://api.elsevier.com/content/abstract/scopus_id/85039733769",
        "dc:identifier": "SCOPUS_ID:85039733769",
        "eid": "2-s2.0-85039733769",
        "dc:title": "Lung nodules: Size still matters",
        "dc:creator": "Larici A.R.",
        "prism:publicationName": "European Respiratory Review",
        "prism:issn": "09059180",
        "prism:eIssn": "16000617",
        "prism:volume": "26",
        "prism:issueIdentifier": "146",
        "prism:pageRange": null,
        "prism:coverDate": "2017-12-31",
        "prism:coverDisplayDate": "31 December 2017",
        "prism:doi": "10.1183/16000617.0025-2017",
        "citedby-count": "119",
        "affiliation": [
            {
                "@_fa": "true",
                "affilname": "Istituto di Radiologia di Universita Cattolica del Sacro Cuore di Roma",
                "affiliation-city": "Rome",
                "affiliation-country": "Italy"
            }
        ],
        "pubmed-id": "29263171",
        "prism:aggregationType": "Journal",
        "subtype": "ar",
        "subtypeDescription": "Article",
        "article-number": "170025",
        "source-id": "18476",
        "openaccess": "1",
        "openaccessFlag": true,
        "freetoread": {
            "value": [
                {
                    "$": "all"
                },
                {
                    "$": "publisherfullgold"
                }
            ]
        },
        "freetoreadLabel": {
            "value": [
                {
                    "$": "All Open Access"
                },
                {
                    "$": "Gold"
                }
            ]
        }
    },
    {
        "@_fa": "true",
        "link": [
            {
                "@_fa": "true",
                "@ref": "self",
                "@href": "https://api.elsevier.com/content/abstract/scopus_id/85039728109"
            },
            {
                "@_fa": "true",
                "@ref": "author-affiliation",
                "@href": "https://api.elsevier.com/content/abstract/scopus_id/85039728109?field=author,affiliation"
            },
            {
                "@_fa": "true",
                "@ref": "scopus",
                "@href": "https://www.scopus.com/inward/record.uri?partnerID=HzOxMe3b&scp=85039728109&origin=inward"
            },
            {
                "@_fa": "true",
                "@ref": "scopus-citedby",
                "@href": "https://www.scopus.com/inward/citedby.uri?partnerID=HzOxMe3b&scp=85039728109&origin=inward"
            }
        ],
        "prism:url": "https://api.elsevier.com/content/abstract/scopus_id/85039728109",
        "dc:identifier": "SCOPUS_ID:85039728109",
        "eid": "2-s2.0-85039728109",
        "dc:title": "Pathobiology of pulmonary arterial hypertension: Understanding the roads less travelled",
        "dc:creator": "Hemnes A.R.",
        "prism:publicationName": "European Respiratory Review",
        "prism:issn": "09059180",
        "prism:eIssn": "16000617",
        "prism:volume": "26",
        "prism:issueIdentifier": "146",
        "prism:pageRange": null,
        "prism:coverDate": "2017-12-31",
        "prism:coverDisplayDate": "31 December 2017",
        "prism:doi": "10.1183/16000617.0093-2017",
        "citedby-count": "74",
        "affiliation": [
            {
                "@_fa": "true",
                "affilname": "Vanderbilt University Medical Center",
                "affiliation-city": "Nashville",
                "affiliation-country": "United States"
            }
        ],
        "pubmed-id": "29263173",
        "prism:aggregationType": "Journal",
        "subtype": "re",
        "subtypeDescription": "Review",
        "article-number": "170093",
        "source-id": "18476",
        "openaccess": "1",
        "openaccessFlag": true,
        "freetoread": {
            "value": [
                {
                    "$": "all"
                },
                {
                    "$": "publisherfullgold"
                },
                {
                    "$": "repository"
                },
                {
                    "$": "repositoryvor"
                }
            ]
        },
        "freetoreadLabel": {
            "value": [
                {
                    "$": "All Open Access"
                },
                {
                    "$": "Gold"
                },
                {
                    "$": "Green"
                }
            ]
        }
    },
    {
        "@_fa": "true",
        "link": [
            {
                "@_fa": "true",
                "@ref": "self",
                "@href": "https://api.elsevier.com/content/abstract/scopus_id/85039719314"
            },
            {
                "@_fa": "true",
                "@ref": "author-affiliation",
                "@href": "https://api.elsevier.com/content/abstract/scopus_id/85039719314?field=author,affiliation"
            },
            {
                "@_fa": "true",
                "@ref": "scopus",
                "@href": "https://www.scopus.com/inward/record.uri?partnerID=HzOxMe3b&scp=85039719314&origin=inward"
            },
            {
                "@_fa": "true",
                "@ref": "scopus-citedby",
                "@href": "https://www.scopus.com/inward/citedby.uri?partnerID=HzOxMe3b&scp=85039719314&origin=inward"
            }
        ],
        "prism:url": "https://api.elsevier.com/content/abstract/scopus_id/85039719314",
        "dc:identifier": "SCOPUS_ID:85039719314",
        "eid": "2-s2.0-85039719314",
        "dc:title": "Metabolic dysfunction in pulmonary hypertension: From basic science to clinical practice",
        "dc:creator": "Chan S.Y.",
        "prism:publicationName": "European Respiratory Review",
        "prism:issn": "09059180",
        "prism:eIssn": "16000617",
        "prism:volume": "26",
        "prism:issueIdentifier": "146",
        "prism:pageRange": null,
        "prism:coverDate": "2017-12-31",
        "prism:coverDisplayDate": "31 December 2017",
        "prism:doi": "10.1183/16000617.0094-2017",
        "citedby-count": "66",
        "affiliation": [
            {
                "@_fa": "true",
                "affilname": "University of Pittsburgh School of Medicine",
                "affiliation-city": "Pittsburgh",
                "affiliation-country": "United States"
            }
        ],
        "pubmed-id": "29263174",
        "prism:aggregationType": "Journal",
        "subtype": "re",
        "subtypeDescription": "Review",
        "article-number": "170094",
        "source-id": "18476",
        "openaccess": "1",
        "openaccessFlag": true,
        "freetoread": {
            "value": [
                {
                    "$": "all"
                },
                {
                    "$": "publisherfullgold"
                }
            ]
        },
        "freetoreadLabel": {
            "value": [
                {
                    "$": "All Open Access"
                },
                {
                    "$": "Gold"
                }
            ]
        }
    },
    {
        "@_fa": "true",
        "link": [
            {
                "@_fa": "true",
                "@ref": "self",
                "@href": "https://api.elsevier.com/content/abstract/scopus_id/85039716712"
            },
            {
                "@_fa": "true",
                "@ref": "author-affiliation",
                "@href": "https://api.elsevier.com/content/abstract/scopus_id/85039716712?field=author,affiliation"
            },
            {
                "@_fa": "true",
                "@ref": "scopus",
                "@href": "https://www.scopus.com/inward/record.uri?partnerID=HzOxMe3b&scp=85039716712&origin=inward"
            },
            {
                "@_fa": "true",
                "@ref": "scopus-citedby",
                "@href": "https://www.scopus.com/inward/citedby.uri?partnerID=HzOxMe3b&scp=85039716712&origin=inward"
            }
        ],
        "prism:url": "https://api.elsevier.com/content/abstract/scopus_id/85039716712",
        "dc:identifier": "SCOPUS_ID:85039716712",
        "eid": "2-s2.0-85039716712",
        "dc:title": "Pulmonary hypertension: A paradigm for rare pulmonary diseases",
        "dc:creator": "Harari S.",
        "prism:publicationName": "European Respiratory Review",
        "prism:issn": "09059180",
        "prism:eIssn": "16000617",
        "prism:volume": "26",
        "prism:issueIdentifier": "146",
        "prism:pageRange": null,
        "prism:coverDate": "2017-12-31",
        "prism:coverDisplayDate": "31 December 2017",
        "prism:doi": "10.1183/16000617.0120-2017",
        "citedby-count": "4",
        "affiliation": [
            {
                "@_fa": "true",
                "affilname": "Ospedale San Giuseppe, Milano",
                "affiliation-city": "Milan",
                "affiliation-country": "Italy"
            }
        ],
        "pubmed-id": "29263177",
        "prism:aggregationType": "Journal",
        "subtype": "ed",
        "subtypeDescription": "Editorial",
        "article-number": "170120",
        "source-id": "18476",
        "openaccess": "1",
        "openaccessFlag": true,
        "freetoread": {
            "value": [
                {
                    "$": "all"
                },
                {
                    "$": "publisherfullgold"
                }
            ]
        },
        "freetoreadLabel": {
            "value": [
                {
                    "$": "All Open Access"
                },
                {
                    "$": "Gold"
                }
            ]
        }
    },
    {
        "@_fa": "true",
        "link": [
            {
                "@_fa": "true",
                "@ref": "self",
                "@href": "https://api.elsevier.com/content/abstract/scopus_id/85039713599"
            },
            {
                "@_fa": "true",
                "@ref": "author-affiliation",
                "@href": "https://api.elsevier.com/content/abstract/scopus_id/85039713599?field=author,affiliation"
            },
            {
                "@_fa": "true",
                "@ref": "scopus",
                "@href": "https://www.scopus.com/inward/record.uri?partnerID=HzOxMe3b&scp=85039713599&origin=inward"
            },
            {
                "@_fa": "true",
                "@ref": "scopus-citedby",
                "@href": "https://www.scopus.com/inward/citedby.uri?partnerID=HzOxMe3b&scp=85039713599&origin=inward"
            }
        ],
        "prism:url": "https://api.elsevier.com/content/abstract/scopus_id/85039713599",
        "dc:identifier": "SCOPUS_ID:85039713599",
        "eid": "2-s2.0-85039713599",
        "dc:title": "Effect of chevron on the decay characteristics of compressible round jet",
        "dc:creator": "Senthil Velavan S.",
        "prism:publicationName": "International Journal of Mechanical and Production Engineering Research and Development",
        "prism:issn": "22496890",
        "prism:eIssn": "22498001",
        "prism:volume": "7",
        "prism:issueIdentifier": "6",
        "prism:pageRange": "679-686",
        "prism:coverDate": "2017-12-31",
        "prism:coverDisplayDate": "31 December 2017",
        "prism:doi": "10.24247/ijmperddec201776",
        "citedby-count": "0",
        "affiliation": [
            {
                "@_fa": "true",
                "affilname": "Sathyabama Institute of Science and Technology",
                "affiliation-city": "Chennai",
                "affiliation-country": "India"
            }
        ],
        "prism:aggregationType": "Journal",
        "subtype": "ar",
        "subtypeDescription": "Article",
        "source-id": "21100814505",
        "openaccess": "1",
        "openaccessFlag": true,
        "freetoread": {
            "value": [
                {
                    "$": "all"
                },
                {
                    "$": "publisherfullgold"
                }
            ]
        },
        "freetoreadLabel": {
            "value": [
                {
                    "$": "All Open Access"
                },
                {
                    "$": "Gold"
                }
            ]
        }
    },
    {
        "@_fa": "true",
        "link": [
            {
                "@_fa": "true",
                "@ref": "self",
                "@href": "https://api.elsevier.com/content/abstract/scopus_id/85039708519"
            },
            {
                "@_fa": "true",
                "@ref": "author-affiliation",
                "@href": "https://api.elsevier.com/content/abstract/scopus_id/85039708519?field=author,affiliation"
            },
            {
                "@_fa": "true",
                "@ref": "scopus",
                "@href": "https://www.scopus.com/inward/record.uri?partnerID=HzOxMe3b&scp=85039708519&origin=inward"
            },
            {
                "@_fa": "true",
                "@ref": "scopus-citedby",
                "@href": "https://www.scopus.com/inward/citedby.uri?partnerID=HzOxMe3b&scp=85039708519&origin=inward"
            }
        ],
        "prism:url": "https://api.elsevier.com/content/abstract/scopus_id/85039708519",
        "dc:identifier": "SCOPUS_ID:85039708519",
        "eid": "2-s2.0-85039708519",
        "dc:title": "Electrical flight technology- A short review and challenges",
        "dc:creator": "Chelladhurai P.S.",
        "prism:publicationName": "International Journal of Mechanical and Production Engineering Research and Development",
        "prism:issn": "22496890",
        "prism:eIssn": "22498001",
        "prism:volume": "7",
        "prism:issueIdentifier": "6",
        "prism:pageRange": "631-640",
        "prism:coverDate": "2017-12-31",
        "prism:coverDisplayDate": "31 December 2017",
        "prism:doi": "10.24247/ijmperddec201771",
        "citedby-count": "0",
        "affiliation": [
            {
                "@_fa": "true",
                "affilname": "St. Theresa International College",
                "affiliation-city": "Bangkok",
                "affiliation-country": "Thailand"
            }
        ],
        "prism:aggregationType": "Journal",
        "subtype": "re",
        "subtypeDescription": "Review",
        "source-id": "21100814505",
        "openaccess": "1",
        "openaccessFlag": true,
        "freetoread": {
            "value": [
                {
                    "$": "all"
                },
                {
                    "$": "publisherfullgold"
                }
            ]
        },
        "freetoreadLabel": {
            "value": [
                {
                    "$": "All Open Access"
                },
                {
                    "$": "Gold"
                }
            ]
        }
    },
    {
        "@_fa": "true",
        "link": [
            {
                "@_fa": "true",
                "@ref": "self",
                "@href": "https://api.elsevier.com/content/abstract/scopus_id/85039699889"
            },
            {
                "@_fa": "true",
                "@ref": "author-affiliation",
                "@href": "https://api.elsevier.com/content/abstract/scopus_id/85039699889?field=author,affiliation"
            },
            {
                "@_fa": "true",
                "@ref": "scopus",
                "@href": "https://www.scopus.com/inward/record.uri?partnerID=HzOxMe3b&scp=85039699889&origin=inward"
            },
            {
                "@_fa": "true",
                "@ref": "scopus-citedby",
                "@href": "https://www.scopus.com/inward/citedby.uri?partnerID=HzOxMe3b&scp=85039699889&origin=inward"
            }
        ],
        "prism:url": "https://api.elsevier.com/content/abstract/scopus_id/85039699889",
        "dc:identifier": "SCOPUS_ID:85039699889",
        "eid": "2-s2.0-85039699889",
        "dc:title": "Pulmonary arterial hypertension: Tailoring treatment to risk in the current era",
        "dc:creator": "Gaine S.",
        "prism:publicationName": "European Respiratory Review",
        "prism:issn": "09059180",
        "prism:eIssn": "16000617",
        "prism:volume": "26",
        "prism:issueIdentifier": "146",
        "prism:pageRange": null,
        "prism:coverDate": "2017-12-31",
        "prism:coverDisplayDate": "31 December 2017",
        "prism:doi": "10.1183/16000617.0095-2017",
        "citedby-count": "34",
        "affiliation": [
            {
                "@_fa": "true",
                "affilname": "University Hospital",
                "affiliation-city": "Dublin",
                "affiliation-country": "Ireland"
            }
        ],
        "pubmed-id": "29263175",
        "prism:aggregationType": "Journal",
        "subtype": "re",
        "subtypeDescription": "Review",
        "article-number": "170095",
        "source-id": "18476",
        "openaccess": "1",
        "openaccessFlag": true,
        "freetoread": {
            "value": [
                {
                    "$": "all"
                },
                {
                    "$": "publisherfullgold"
                },
                {
                    "$": "repository"
                },
                {
                    "$": "repositoryvor"
                }
            ]
        },
        "freetoreadLabel": {
            "value": [
                {
                    "$": "All Open Access"
                },
                {
                    "$": "Gold"
                },
                {
                    "$": "Green"
                }
            ]
        }
    },
    {
        "@_fa": "true",
        "link": [
            {
                "@_fa": "true",
                "@ref": "self",
                "@href": "https://api.elsevier.com/content/abstract/scopus_id/85039698252"
            },
            {
                "@_fa": "true",
                "@ref": "author-affiliation",
                "@href": "https://api.elsevier.com/content/abstract/scopus_id/85039698252?field=author,affiliation"
            },
            {
                "@_fa": "true",
                "@ref": "scopus",
                "@href": "https://www.scopus.com/inward/record.uri?partnerID=HzOxMe3b&scp=85039698252&origin=inward"
            },
            {
                "@_fa": "true",
                "@ref": "scopus-citedby",
                "@href": "https://www.scopus.com/inward/citedby.uri?partnerID=HzOxMe3b&scp=85039698252&origin=inward"
            }
        ],
        "prism:url": "https://api.elsevier.com/content/abstract/scopus_id/85039698252",
        "dc:identifier": "SCOPUS_ID:85039698252",
        "eid": "2-s2.0-85039698252",
        "dc:title": "Effects of ultraviolet radiation with and without heat, on the fatigue behavior of below-knee prosthetic sockets",
        "dc:creator": "Hussien Z.Y.",
        "prism:publicationName": "International Journal of Mechanical and Production Engineering Research and Development",
        "prism:issn": "22496890",
        "prism:eIssn": "22498001",
        "prism:volume": "7",
        "prism:issueIdentifier": "6",
        "prism:pageRange": "641-652",
        "prism:coverDate": "2017-12-31",
        "prism:coverDisplayDate": "31 December 2017",
        "prism:doi": "10.24247/ijmperddec201772",
        "citedby-count": "49",
        "affiliation": [
            {
                "@_fa": "true",
                "affilname": "Mustansiriyah University",
                "affiliation-city": "Baghdad",
                "affiliation-country": "Iraq"
            }
        ],
        "prism:aggregationType": "Journal",
        "subtype": "ar",
        "subtypeDescription": "Article",
        "source-id": "21100814505",
        "openaccess": "1",
        "openaccessFlag": true,
        "freetoread": {
            "value": [
                {
                    "$": "all"
                },
                {
                    "$": "publisherfullgold"
                }
            ]
        },
        "freetoreadLabel": {
            "value": [
                {
                    "$": "All Open Access"
                },
                {
                    "$": "Gold"
                }
            ]
        }
    }
]